settings.py
spark_job_handler.py
spark_yarn_submit-1.0.0.dist-info/DESCRIPTION.rst
spark_yarn_submit-1.0.0.dist-info/METADATA
spark_yarn_submit-1.0.0.dist-info/RECORD
spark_yarn_submit-1.0.0.dist-info/WHEEL
spark_yarn_submit-1.0.0.dist-info/metadata.json
spark_yarn_submit-1.0.0.dist-info/top_level.txt
