Metadata-Version: 2.0
Name: spark-yarn-submit
Version: 1.0.0
Summary: library to handle spark job submit in a yarn cluster in different environment
Home-page: https://github.com/s8sg/spark-py-submit
Author: Swarvanu Sengupta (s8sg)
Author-email: swarvanusg@gmail.com
License: MIT
Keywords: spark yarn submit bigdata hadoop
Platform: UNKNOWN
Classifier: Development Status :: 3 - Alpha
Classifier: Intended Audience :: Developers
Classifier: Topic :: Software Development :: Build Tools
Classifier: License :: OSI Approved :: MIT License
Classifier: Programming Language :: Python :: 2
Classifier: Programming Language :: Python :: 2.6
Classifier: Programming Language :: Python :: 2.7
Classifier: Programming Language :: Python :: 3
Classifier: Programming Language :: Python :: 3.3
Classifier: Programming Language :: Python :: 3.4
Classifier: Programming Language :: Python :: 3.5
